transformer_embeddings/__init__.py
transformer_embeddings/helpers.py
transformer_embeddings/model.py
transformer_embeddings/poolers.py
transformer_embeddings-4.0.14.dist-info/LICENSE
transformer_embeddings-4.0.14.dist-info/METADATA
transformer_embeddings-4.0.14.dist-info/WHEEL
transformer_embeddings-4.0.14.dist-info/RECORD
