Metadata-Version: 2.1
Name: transformer-embeddings
Version: 4.0.14
Summary: Transformer Embeddings
Home-page: https://github.com/HeadspaceMeditation/transformer-embeddings
License: Apache-2.0
Author: Headspace Health
Author-email: transformer-embeddings@headspace.com
Requires-Python: >=3.8,<3.11
Classifier: Development Status :: 5 - Production/Stable
Classifier: License :: OSI Approved :: Apache Software License
Classifier: Programming Language :: Python :: 3
Classifier: Programming Language :: Python :: 3.8
Classifier: Programming Language :: Python :: 3.9
Classifier: Programming Language :: Python :: 3.10
Provides-Extra: s3
Requires-Dist: s3fs (>=2023.1.0,<2024.0.0) ; extra == "s3"
Requires-Dist: torch (>=1.9.1,<2.0.0)
Requires-Dist: transformers (>=4.36.0,<5.0.0)
Project-URL: Changelog, https://github.com/HeadspaceMeditation/transformer-embeddings/releases
Project-URL: Documentation, https://github.com/HeadspaceMeditation/transformer-embeddings
Project-URL: Repository, https://github.com/HeadspaceMeditation/transformer-embeddings
